kffmpeg/__init__.py
kffmpeg/ffmpeg.py
kffmpeg/ffprobe.py
kffmpeg-0.2.46.dist-info/LICENSE
kffmpeg-0.2.46.dist-info/METADATA
kffmpeg-0.2.46.dist-info/WHEEL
kffmpeg-0.2.46.dist-info/top_level.txt
kffmpeg-0.2.46.dist-info/RECORD
