Metadata-Version: 2.1
Name: kffmpeg
Version: 0.2.46
Summary: kffmpeg
Home-page: https://github.com/kkristof200/kffmpeg
Author: Kovacs Kristof-Attila
Classifier: Programming Language :: Python :: 3
Classifier: License :: OSI Approved :: MIT License
Classifier: Operating System :: OS Independent
Requires-Python: >=3.5
License-File: LICENSE
Requires-Dist: kcu (>=0.0.73)
Requires-Dist: setuptools (>=62.2.0)
